torchsim/__init__.py
torchsim/_version.py
torchsim/_functional/__init__.py
torchsim/_functional/_bssfp.py
torchsim/_functional/_fse.py
torchsim/_functional/_mp2rage.py
torchsim/_functional/_mpnrage.py
torchsim/_functional/_mprage.py
torchsim/_functional/_mrf.py
torchsim/_functional/_spgr.py
torchsim/base/__init__.py
torchsim/base/base.py
torchsim/base/config/__init__.py
torchsim/base/config/environment.py
torchsim/base/config/relax_model.py
torchsim/base/decorators/__init__.py
torchsim/base/decorators/_autocast.py
torchsim/base/decorators/_broadcast.py
torchsim/base/decorators/_jacfwd.py
torchsim/epg/__init__.py
torchsim/epg/_adc.py
torchsim/epg/_adiabatic_inversion.py
torchsim/epg/_diffusion.py
torchsim/epg/_flow.py
torchsim/epg/_longitudinal_relaxation.py
torchsim/epg/_rf_pulse.py
torchsim/epg/_shift.py
torchsim/epg/_spoil.py
torchsim/epg/_states_matrix.py
torchsim/epg/_transverse_relaxation.py
torchsim/epg/_utils.py
torchsim/models/__init__.py
torchsim/models/bssfp.py
torchsim/models/fse.py
torchsim/models/mp2rage.py
torchsim/models/mpnrage.py
torchsim/models/mprage.py
torchsim/models/mrf.py
torchsim/models/spgr.py
torchsim/utils/__init__.py
torchsim/utils/_b1rms.py
torchsim/utils/_slice_prof.py
torchsim-0.0.3.dist-info/LICENSE.txt
torchsim-0.0.3.dist-info/METADATA
torchsim-0.0.3.dist-info/WHEEL
torchsim-0.0.3.dist-info/top_level.txt
torchsim-0.0.3.dist-info/RECORD
