Metadata-Version: 2.1
Name: torchsim
Version: 0.0.3
Summary: A feature-rich MR simulator supporting massive parallelization on GPU and automatic differentiation.
Author-email: Matteo Cencini <matteo.cencini@gmail.com>
Project-URL: Homepage, https://github.com/INFN-MRI/torchsim
Project-URL: Bug Reports, https://github.com/INFN-MRI/torchsim/issues
Project-URL: Source, https://github.com/INFN-MRI/torchsim
Keywords: epg,mri,simulation,bloch
Classifier: Development Status :: 3 - Alpha
Classifier: Intended Audience :: Developers
Classifier: License :: OSI Approved :: MIT License
Classifier: Programming Language :: Python :: 3.10
Classifier: Programming Language :: Python :: 3.11
Classifier: Programming Language :: Python :: 3.12
Requires-Python: >=3.10
License-File: LICENSE.txt
Requires-Dist: scipy
Requires-Dist: torch
Requires-Dist: mri-nufft
Provides-Extra: dev
Requires-Dist: black; extra == "dev"
Requires-Dist: isort; extra == "dev"
Provides-Extra: test
Requires-Dist: pytest; extra == "test"
Requires-Dist: pytest-black; extra == "test"
Requires-Dist: pytest-cov; extra == "test"
Requires-Dist: pytest-sugar; extra == "test"
Requires-Dist: pytest-xdist; extra == "test"
Provides-Extra: doc
Requires-Dist: sphinx; extra == "doc"
Requires-Dist: sphinx_book_theme; extra == "doc"
Requires-Dist: sphinx-gallery; extra == "doc"
Requires-Dist: sphinx-exec-directive; extra == "doc"
Requires-Dist: sphinx_copybutton; extra == "doc"
Requires-Dist: matplotlib; extra == "doc"
Requires-Dist: sigpy; extra == "doc"
Requires-Dist: torchio; extra == "doc"
Requires-Dist: numba; extra == "doc"
Requires-Dist: ipywidgets; extra == "doc"
